<?xml version="1.0" encoding="utf-8"?>
<skin version="1.0" load="1" type="string" language="EN">
  <String>
    <String id="IDS_APP_NAME">ActivCast 2.0</String>
    <String id="IDS_PANEL_ID_INVALID_TIPS">Error en el ID del panel. Vuelva a intentarlo.</String>
    <String id="IDS_NAME_EMPTY_TIPS">Especifique su nombre.</String>
    <String id="IDS_CAST">TRANSMITIR</String>
	<String id="IDS_ENTER_WAITING_ROOM">ENTRAR EN LA SALA DE ESPERA</String>
    <String id="IDS_CANCEL">CANCELAR</String>
    <String id="IDS_YES">SÍ</String>
    <String id="IDS_NO">NO</String>
	<String id="IDS_STOP_CASTING">DEJAR DE TRANSMITIR</String>
	<String id="IDS_CASTING_TITLE_TIPS">Transmitir pantalla al ActivPanel</String>
	<String id="IDS_CASTING_TO_NAME">Transmitir a </String>	
	<String id="IDS_TYPE_IN_PANELID_1">Escriba el</String>
	<String id="IDS_TYPE_IN_PANELID_2"> ID del panel </String>
	<String id="IDS_TYPE_IN_PANELID_3">tal y como aparece en ActivCast 2.0 en el ActivPanel.</String>	
	<String id="IDS_UESRNAME_EMPTY_TIPS">Su nombre</String>
	<String id="IDS_TOUCHBACK_TITLE_TIPS">Control desde el panel (duplicación bidireccional)</String>
	<String id="IDS_TOUCHBACK_ENABLE_TIPS">Habilite la duplicación bidireccional para que el ActivPanel pueda navegar por su pantalla.</String>	
	<String id="IDS_IN_WAITING_ROOM">Está en la sala de espera</String>
	<String id="IDS_WAITING_ROOM_TIPS">Espere hasta tener permiso para transmitir su pantalla.</String>
	<String id="IDS_YOU_ARE_CASTING_TIPS"> está transmitiendo ahora a </String>	
	<String id="IDS_WARNING">ADVERTENCIA</String>
	<String id="IDS_RESTART_TIPS">Se ha cambiado la tarjeta de sonido predeterminada. Para poder usarla correctamente, deje de transmitir y transmita de nuevo.</String>
  </String>
</skin>