<?xml version="1.0" encoding="utf-8"?>
<skin version="1.0" load="1" type="string" language="EN">
  <String>
    <String id="IDS_APP_NAME">ActivCast 2.0</String>
    <String id="IDS_PANEL_ID_INVALID_TIPS">Feil med skjerm-ID. Prøv en gang til.</String>
    <String id="IDS_NAME_EMPTY_TIPS">Skriv inn navnet ditt.</String>
    <String id="IDS_CAST">START SENDING</String>
	<String id="IDS_ENTER_WAITING_ROOM">ÅPNE VENTEROM</String>
    <String id="IDS_CANCEL">AVBRYT</String>
    <String id="IDS_YES">JA</String>
    <String id="IDS_NO">NEI</String>
	<String id="IDS_STOP_CASTING">STOPP SENDING</String>
	<String id="IDS_CASTING_TITLE_TIPS">Send skjerm til ActivPanel</String>
	<String id="IDS_CASTING_TO_NAME">Send til </String>	
	<String id="IDS_TYPE_IN_PANELID_1">Angi</String>
	<String id="IDS_TYPE_IN_PANELID_2"> Skjerm-ID </String>
	<String id="IDS_TYPE_IN_PANELID_3">som vist i ActivCast 2.0 på ActivPanel.</String>	
	<String id="IDS_UESRNAME_EMPTY_TIPS">Ditt navn</String>
	<String id="IDS_TOUCHBACK_TITLE_TIPS">Kontroller fra panel (touchback)</String>
	<String id="IDS_TOUCHBACK_ENABLE_TIPS">Aktiver touchback slik at ActivPanel kan navigere skjermen din.</String>	
	<String id="IDS_IN_WAITING_ROOM">Du er på venterommet</String>
	<String id="IDS_WAITING_ROOM_TIPS">Vent på tillatelse til å sende skjermen din.</String>
	<String id="IDS_YOU_ARE_CASTING_TIPS"> sender nå til </String>	
	<String id="IDS_WARNING">ADVARSEL</String>
	<String id="IDS_RESTART_TIPS">Standardlydkortet har blitt endret. For å bruke det riktig må du stoppe sending og starte sending på nytt.</String>
  </String>
</skin>